st_hierarchicalGrid/__init__.py
st_hierarchicalGrid/frontend/build/asset-manifest.json
st_hierarchicalGrid/frontend/build/bootstrap.min.css
st_hierarchicalGrid/frontend/build/index.html
st_hierarchicalGrid/frontend/build/static/js/239.f2189406.chunk.js
st_hierarchicalGrid/frontend/build/static/js/239.f2189406.chunk.js.LICENSE.txt
st_hierarchicalGrid/frontend/build/static/js/239.f2189406.chunk.js.map
st_hierarchicalGrid/frontend/build/static/js/732.c24ff1d5.chunk.js
st_hierarchicalGrid/frontend/build/static/js/732.c24ff1d5.chunk.js.map
st_hierarchicalGrid/frontend/build/static/js/977.2f56a4d3.chunk.js
st_hierarchicalGrid/frontend/build/static/js/977.2f56a4d3.chunk.js.LICENSE.txt
st_hierarchicalGrid/frontend/build/static/js/977.2f56a4d3.chunk.js.map
st_hierarchicalGrid/frontend/build/static/js/main.0fbdb6ae.js
st_hierarchicalGrid/frontend/build/static/js/main.0fbdb6ae.js.LICENSE.txt
st_hierarchicalGrid/frontend/build/static/js/main.0fbdb6ae.js.map
st_organogramRTR/__init__.py
st_organogramRTR/frontend/build/asset-manifest.json
st_organogramRTR/frontend/build/bootstrap.min.css
st_organogramRTR/frontend/build/index.html
st_organogramRTR/frontend/build/static/js/main.11de270d.js
st_organogramRTR/frontend/build/static/js/main.11de270d.js.LICENSE.txt
st_organogramRTR/frontend/build/static/js/main.11de270d.js.map
st_organogramRTR/frontend/dist/index.html
st_organogramRTR/frontend/dist/vite.svg
st_organogramRTR/frontend/dist/assets/index-BAe2MxOx.css
st_organogramRTR/frontend/dist/assets/index-D44RLzGG.js
streamlit_organizational_rtr_chart2-0.0.1.dist-info/licenses/LICENSE
streamlit_organizational_rtr_chart2-0.0.1.dist-info/METADATA
streamlit_organizational_rtr_chart2-0.0.1.dist-info/WHEEL
streamlit_organizational_rtr_chart2-0.0.1.dist-info/top_level.txt
streamlit_organizational_rtr_chart2-0.0.1.dist-info/RECORD
